{"status": 0, "nodelist": [{"id": "1239", "name": "gnid:6255148", "label": "Europe"}, {"id": "1410", "name": "gnid:2782113", "label": "Austria", "wikipedia": "en.wikipedia.org/wiki/Austria", "lng": "13.33333", "lat": "47.33333"}, {"id": "1530", "name": "gnid:2763586", "label": "Tyrol", "wikipedia": "en.wikipedia.org/wiki/Tyrol_%28state%29", "lng": "11.33333", "lat": "47.25"}, {"id": "1617", "name": "gnid:2775219", "label": "Innsbruck-Land District", "wikipedia": "en.wikipedia.org/wiki/Innsbruck-Land_District", "lng": "11.33333", "lat": "47.2"}, {"id": "1618", "name": "gnid:2760523", "label": "Zirl", "lng": "11.23333", "lat": "47.28333"}], "userdata": {"lang": "en", "language_id": "4"}}