{"status": 0, "nodelist": [{"id": "1239", "name": "gnid:6255148", "label": "Europe"}, {"id": "2207", "name": "gnid:3144096", "label": "Kingdom of Norway", "wikipedia": "en.wikipedia.org/wiki/Norway", "lng": "10", "lat": "62"}, {"id": "2208", "name": "gnid:3133897", "label": "Troms Fylke", "wikipedia": "en.wikipedia.org/wiki/Troms", "lng": "18.9445", "lat": "69.6442"}, {"id": "2209", "name": "gnid:6453316", "label": "Troms\u00f8", "wikipedia": "en.wikipedia.org/wiki/Troms%C3%B8", "lng": "18.95702", "lat": "69.64961"}, {"id": "2210", "name": "gnid:3133904", "label": "Tromsdalen", "wikipedia": "en.wikipedia.org/wiki/Tromsdalen", "lng": "19.01667", "lat": "69.65"}], "userdata": {"lang": "en", "language_id": "4"}}