{"status": 0, "nodelist": [{"id": "1239", "name": "gnid:6255148", "label": "Europe"}, {"id": "1834", "name": "gnid:3175395", "label": "Italy", "wikipedia": "en.wikipedia.org/wiki/Italy", "lng": "12.83333", "lat": "42.83333"}, {"id": "2235", "name": "gnid:3164604", "label": "Veneto", "wikipedia": "en.wikipedia.org/wiki/Veneto", "lng": "11.75", "lat": "45.5"}, {"id": "2408", "name": "gnid:3165200", "label": "Provincia di Treviso", "wikipedia": "en.wikipedia.org/wiki/Province_of_Treviso", "lng": "12.21667", "lat": "45.83333"}, {"id": "2409", "name": "gnid:8949902", "label": "Pagnano", "lng": "11.88876", "lat": "45.8088"}], "userdata": {"lang": "en", "language_id": "4"}}