{"status": 0, "nodelist": [{"id": "2677", "name": "gnid:6255146", "label": "Africa", "wikipedia": "en.wikipedia.org/wiki/Africa", "lng": "21.09375", "lat": "7.1881"}, {"id": "2678", "name": "gnid:357994", "label": "Egypt", "wikipedia": "en.wikipedia.org/wiki/Egypt", "lng": "30", "lat": "27"}, {"id": "2889", "name": "gnid:350546", "label": "Mu\u1e29\u0101faz\u0327at Qin\u0101", "wikipedia": "en.wikipedia.org/wiki/Qena_Governorate", "lng": "32.75", "lat": "25.8"}, {"id": "2890", "name": "gnid:358422", "label": "Dandarah", "wikipedia": "en.wikipedia.org/wiki/Dendera", "lng": "32.65776", "lat": "26.16817"}], "userdata": {"lang": "en", "language_id": "4"}}