{"status": 0, "nodelist": [{"id": "1283", "name": "gnid:6255147", "label": "Asia", "wikipedia": "en.wikipedia.org/wiki/Asia", "lng": "89.29688", "lat": "29.84064"}, {"id": "1284", "name": "gnid:1643084", "label": "Indonesia", "wikipedia": "en.wikipedia.org/wiki/Indonesia", "lng": "120", "lat": "-5"}, {"id": "3935", "name": "gnid:1215638", "label": "Special Region of Aceh", "wikipedia": "en.wikipedia.org/wiki/Aceh", "lng": "97", "lat": "4"}, {"id": "3936", "name": "gnid:1214026", "label": "Sabang", "wikipedia": "en.wikipedia.org/wiki/Sabang%2C_Indonesia", "lng": "95.31644", "lat": "5.88969"}], "userdata": {"lang": "en", "language_id": "4"}}