{"status": 0, "nodelist": [{"id": "1239", "name": "gnid:6255148", "label": "Europe"}, {"id": "1834", "name": "gnid:3175395", "label": "Italy", "wikipedia": "en.wikipedia.org/wiki/Italy", "lng": "12.83333", "lat": "42.83333"}, {"id": "3611", "name": "gnid:3177401", "label": "Emilia-Romagna", "wikipedia": "en.wikipedia.org/wiki/Emilia_%28region_of_Italy%29", "lng": "10.98361", "lat": "44.5444"}, {"id": "4027", "name": "gnid:3169560", "label": "Provincia di Ravenna", "wikipedia": "en.wikipedia.org/wiki/Province_of_Ravenna", "lng": "11.98333", "lat": "44.41667"}, {"id": "4028", "name": "gnid:3169561", "label": "Ravenna", "wikipedia": "en.wikipedia.org/wiki/Ravenna", "lng": "12.20121", "lat": "44.41344"}], "userdata": {"lang": "en", "language_id": "4"}}