{"status": 0, "nodelist": [{"id": "1239", "name": "gnid:6255148", "label": "Europe"}, {"id": "1240", "name": "gnid:2658434", "label": "Switzerland"}, {"id": "1241", "name": "gnid:2658563", "label": "Canton of Solothurn"}, {"id": "1276", "name": "gnid:6458779", "label": "Bezirk Solothurn", "lng": "7.53084", "lat": "47.20818"}, {"id": "1277", "name": "gnid:2658564", "label": "Solothurn", "wikipedia": "en.wikipedia.org/wiki/Solothurn", "lng": "7.53714", "lat": "47.20791"}], "userdata": {"lang": "en", "language_id": "4"}}