{"status": 0, "nodelist": [{"id": "1239", "name": "gnid:6255148", "label": "Europe"}, {"id": "1240", "name": "gnid:2658434", "label": "Switzerland"}, {"id": "1316", "name": "gnid:2661551", "label": "Bern", "wikipedia": "en.wikipedia.org/wiki/Canton_of_Bern", "lng": "7.59563", "lat": "46.87251"}, {"id": "1518", "name": "gnid:8260136", "label": "Biel/Bienne", "lng": "7.26174", "lat": "47.12725"}, {"id": "1519", "name": "gnid:2658284", "label": "Twann", "wikipedia": "en.wikipedia.org/wiki/Twann", "lng": "7.15699", "lat": "47.0942"}], "userdata": {"lang": "en", "language_id": "4"}}