{"status": 0, "nodelist": [{"id": "1239", "name": "gnid:6255148", "label": "Europe"}, {"id": "1240", "name": "gnid:2658434", "label": "Switzerland"}, {"id": "1324", "name": "gnid:2661739", "label": "Canton of Appenzell Ausserrhoden", "wikipedia": "en.wikipedia.org/wiki/Appenzell_Ausserrhoden", "lng": "9.39818", "lat": "47.38937"}, {"id": "1513", "name": "gnid:6458830", "label": "Bezirk Mittelland", "lng": "9.43469", "lat": "47.377"}, {"id": "1947", "name": "gnid:2661343", "label": "B\u00fchler", "wikipedia": "en.wikipedia.org/wiki/B%C3%BChler", "lng": "9.42507", "lat": "47.37348"}], "userdata": {"lang": "en", "language_id": "4"}}